README.rst
setup.py
isight/__init__.py
isight/isight.py
isight.egg-info/PKG-INFO
isight.egg-info/SOURCES.txt
isight.egg-info/dependency_links.txt
isight.egg-info/not-zip-safe
isight.egg-info/top_level.txt