Metadata-Version: 1.0
Name: isight
Version: 0.7
Summary: Library to submit queries to iSIGHT API and return the result back
Home-page: https://github.com/maltantawy/iSIGHT-api
Author: Mostafa Altantawy
Author-email: mostafa.altantawy@gmail.com
License: GPL
Platform: UNKNOWN
